{
    "title": "Men's 500 m - Speed Skating Sapporo 1972 Winter Olympics",
    "year": 1972,
    "distance": "500 m",
    "sex": "Men",
    "table": "{\"0\":{\"0\":null,\"1\":\"Men's 500 m 1972\",\"2\":null,\"3\":\"Final\",\"4\":null,\"5\":null,\"6\":null,\"7\":null,\"8\":\"4.\",\"9\":\"5.\",\"10\":\"6.\",\"11\":\"7.\",\"12\":\"8.\",\"13\":\"9.\",\"14\":\"10.\",\"15\":\"11.\",\"16\":\"12.\",\"17\":\"13.\",\"18\":\"14.\",\"19\":\"15.\",\"20\":\"16.\",\"21\":\"17.\",\"22\":\"18.\",\"23\":\"19.\",\"24\":\"20.\",\"25\":\"21.\",\"26\":\"22.\",\"27\":\"23.\",\"28\":\"24.\",\"29\":\"25.\",\"30\":\"-\",\"31\":\"27.\",\"32\":\"28.\",\"33\":\"29.\",\"34\":\"30.\",\"35\":\"31.\",\"36\":\"32.\",\"37\":\"33.\",\"38\":\"34.\",\"39\":\"35.\",\"40\":\"36.\",\"41\":null,\"42\":null,\"43\":null,\"44\":null,\"45\":\"Men's 500 m - Speed Skating - Sapporo 1972 Winter Olympics Event Format:  Skaters raced against the clock although they raced in pairs on separate lanes on an oval rink (inner and outer lanes). Skaters had to change lanes in the back straightaway of each lap in order to skate an equal distance. The skater on the outer lane had the right of way and the skater leaving the inner lane should avoid collision. The Olympic gold medal winner was the athlete with the fastest time for the race. Event facts: Men's 500 m competition was held at the Makomanai Speed Skating Rink and 37 athletes participated in the event.\",\"46\":null,\"47\":\"These results for Men's 500 m - Sapporo 1972 Winter Olympics - are based on the official olympic reports and the Olympian Database\",\"48\":null},\"1\":{\"0\":null,\"1\":\"Men's 500 m 1972\",\"2\":null,\"3\":\"Final\",\"4\":null,\"5\":\"Erhard Keller\",\"6\":\"Hasse B\\u00f6rjes\",\"7\":\"Valery Muratov\",\"8\":\"Per Bj\\u00f8rang\",\"9\":\"Seppo H\\u00e4nninen\",\"10\":\"Leo Linkovesi\",\"11\":\"Ove K\\u00f6nig\",\"12\":\"Masaki Suzuki\",\"13\":\"Mats Wallberg\",\"14\":\"Hans Lichtenstern\",\"15\":\"Peter Eberling\",\"16\":\"Lasse Efskind\",\"17\":\"Takayuki Hida\",\"18\":\"Vladimir Komarov\",\"19\":\"Neil Blatchford\",\"20\":\"Johan Granath\",\"21\":\"Norio Hirate\",\"22\":\"Johan Lind\",\"23\":\"Keiichi Suzuki\",\"24\":\"Gregory Lyman\",\"25\":\"Gerhard Zimmermann\",\"26\":\"Jung Chung-ku\",\"27\":\"Otmar Braunecker\",\"28\":\"David Hampton\",\"29\":\"Bruno Toniolli\",\"30\":\"Frits Verheijen\",\"31\":\"Jouko Salakka\",\"32\":\"Luvsanlkhagvyn Dashnyam\",\"33\":\"Gerard Cassan\",\"34\":\"John Cassidy\",\"35\":\"Herbert Schwarz\",\"36\":\"Jacob van Dijk\",\"37\":\"Richard Tourne\",\"38\":\"Ard Schenk\",\"39\":\"James Lynch\",\"40\":\"Colin Coates\",\"41\":\"John Wurster\",\"42\":\"Ole Christian Iversen\",\"43\":null,\"44\":null,\"45\":\"Men's 500 m - Speed Skating - Sapporo 1972 Winter Olympics Event Format:  Skaters raced against the clock although they raced in pairs on separate lanes on an oval rink (inner and outer lanes). Skaters had to change lanes in the back straightaway of each lap in order to skate an equal distance. The skater on the outer lane had the right of way and the skater leaving the inner lane should avoid collision. The Olympic gold medal winner was the athlete with the fastest time for the race. Event facts: Men's 500 m competition was held at the Makomanai Speed Skating Rink and 37 athletes participated in the event.\",\"46\":null,\"47\":\"These results for Men's 500 m - Sapporo 1972 Winter Olympics - are based on the official olympic reports and the Olympian Database\",\"48\":null},\"2\":{\"0\":null,\"1\":\"Men's 500 m 1972\",\"2\":null,\"3\":\"Final\",\"4\":null,\"5\":null,\"6\":null,\"7\":null,\"8\":null,\"9\":null,\"10\":null,\"11\":null,\"12\":null,\"13\":null,\"14\":null,\"15\":null,\"16\":null,\"17\":null,\"18\":null,\"19\":null,\"20\":null,\"21\":null,\"22\":null,\"23\":null,\"24\":null,\"25\":null,\"26\":null,\"27\":null,\"28\":null,\"29\":null,\"30\":null,\"31\":null,\"32\":null,\"33\":null,\"34\":null,\"35\":null,\"36\":null,\"37\":null,\"38\":null,\"39\":null,\"40\":null,\"41\":null,\"42\":null,\"43\":null,\"44\":null,\"45\":\"Men's 500 m - Speed Skating - Sapporo 1972 Winter Olympics Event Format:  Skaters raced against the clock although they raced in pairs on separate lanes on an oval rink (inner and outer lanes). Skaters had to change lanes in the back straightaway of each lap in order to skate an equal distance. The skater on the outer lane had the right of way and the skater leaving the inner lane should avoid collision. The Olympic gold medal winner was the athlete with the fastest time for the race. Event facts: Men's 500 m competition was held at the Makomanai Speed Skating Rink and 37 athletes participated in the event.\",\"46\":null,\"47\":\"These results for Men's 500 m - Sapporo 1972 Winter Olympics - are based on the official olympic reports and the Olympian Database\",\"48\":null},\"3\":{\"0\":null,\"1\":\"Men's 500 m 1972\",\"2\":null,\"3\":\"Final\",\"4\":null,\"5\":\"FRG\",\"6\":\"SWE\",\"7\":\"URS\",\"8\":\"NOR\",\"9\":\"FIN\",\"10\":\"FIN\",\"11\":\"SWE\",\"12\":\"JPN\",\"13\":\"SWE\",\"14\":\"FRG\",\"15\":\"USA\",\"16\":\"NOR\",\"17\":\"JPN\",\"18\":\"URS\",\"19\":\"USA\",\"20\":\"SWE\",\"21\":\"JPN\",\"22\":\"NOR\",\"23\":\"JPN\",\"24\":\"USA\",\"25\":\"FRG\",\"26\":\"KOR\",\"27\":\"AUT\",\"28\":\"GBR\",\"29\":\"ITA\",\"30\":\"NED\",\"31\":\"FIN\",\"32\":\"MGL\",\"33\":\"CAN\",\"34\":\"CAN\",\"35\":\"FRG\",\"36\":\"NED\",\"37\":\"FRA\",\"38\":\"NED\",\"39\":\"AUS\",\"40\":\"AUS\",\"41\":\"USA\",\"42\":\"NOR\",\"43\":null,\"44\":null,\"45\":\"Men's 500 m - Speed Skating - Sapporo 1972 Winter Olympics Event Format:  Skaters raced against the clock although they raced in pairs on separate lanes on an oval rink (inner and outer lanes). Skaters had to change lanes in the back straightaway of each lap in order to skate an equal distance. The skater on the outer lane had the right of way and the skater leaving the inner lane should avoid collision. The Olympic gold medal winner was the athlete with the fastest time for the race. Event facts: Men's 500 m competition was held at the Makomanai Speed Skating Rink and 37 athletes participated in the event.\",\"46\":null,\"47\":\"These results for Men's 500 m - Sapporo 1972 Winter Olympics - are based on the official olympic reports and the Olympian Database\",\"48\":null},\"4\":{\"0\":null,\"1\":\"Men's 500 m 1972\",\"2\":null,\"3\":\"Final\",\"4\":null,\"5\":\"3944\",\"6\":\"3969\",\"7\":\"3980\",\"8\":\"3991\",\"9\":\"4012\",\"10\":\"4014\",\"11\":\"4025\",\"12\":\"4035\",\"13\":\"4041\",\"14\":\"4055\",\"15\":\"4058\",\"16\":\"4060\",\"17\":\"4062\",\"18\":\"4065\",\"19\":\"4067\",\"20\":\"4079\",\"21\":\"4108\",\"22\":\"4114\",\"23\":\"4128\",\"24\":\"4130\",\"25\":\"4135\",\"26\":\"4142\",\"27\":\"4214\",\"28\":\"4259\",\"29\":\"4267\",\"30\":\"4267\",\"31\":\"4281\",\"32\":\"4286\",\"33\":\"4287\",\"34\":\"4301\",\"35\":\"4303\",\"36\":\"4304\",\"37\":\"4306\",\"38\":\"4340\",\"39\":\"4351\",\"40\":\"4474\",\"41\":\"dnf\",\"42\":\"dnf\",\"43\":null,\"44\":null,\"45\":\"Men's 500 m - Speed Skating - Sapporo 1972 Winter Olympics Event Format:  Skaters raced against the clock although they raced in pairs on separate lanes on an oval rink (inner and outer lanes). Skaters had to change lanes in the back straightaway of each lap in order to skate an equal distance. The skater on the outer lane had the right of way and the skater leaving the inner lane should avoid collision. The Olympic gold medal winner was the athlete with the fastest time for the race. Event facts: Men's 500 m competition was held at the Makomanai Speed Skating Rink and 37 athletes participated in the event.\",\"46\":null,\"47\":\"These results for Men's 500 m - Sapporo 1972 Winter Olympics - are based on the official olympic reports and the Olympian Database\",\"48\":null},\"5\":{\"0\":null,\"1\":\"Men's 500 m 1972\",\"2\":null,\"3\":\"Final\",\"4\":null,\"5\":\"OR\",\"6\":null,\"7\":null,\"8\":null,\"9\":null,\"10\":null,\"11\":null,\"12\":null,\"13\":null,\"14\":null,\"15\":null,\"16\":null,\"17\":null,\"18\":null,\"19\":null,\"20\":null,\"21\":null,\"22\":null,\"23\":null,\"24\":null,\"25\":null,\"26\":null,\"27\":null,\"28\":null,\"29\":null,\"30\":null,\"31\":null,\"32\":null,\"33\":null,\"34\":null,\"35\":null,\"36\":null,\"37\":null,\"38\":null,\"39\":null,\"40\":null,\"41\":null,\"42\":null,\"43\":null,\"44\":null,\"45\":\"Men's 500 m - Speed Skating - Sapporo 1972 Winter Olympics Event Format:  Skaters raced against the clock although they raced in pairs on separate lanes on an oval rink (inner and outer lanes). Skaters had to change lanes in the back straightaway of each lap in order to skate an equal distance. The skater on the outer lane had the right of way and the skater leaving the inner lane should avoid collision. The Olympic gold medal winner was the athlete with the fastest time for the race. Event facts: Men's 500 m competition was held at the Makomanai Speed Skating Rink and 37 athletes participated in the event.\",\"46\":null,\"47\":\"These results for Men's 500 m - Sapporo 1972 Winter Olympics - are based on the official olympic reports and the Olympian Database\",\"48\":null}}",
    "id": 12032
}